foxdemo/__init__.py
foxdemo/common/__init__.py
foxdemo/common/config.py
foxdemo/common/controller.py
foxdemo/common/converters.py
foxdemo/common/flask.py
foxdemo/common/mongo_util.py
foxdemo/common/persistence_models.py
foxdemo_lib-1.0.2.dist-info/METADATA
foxdemo_lib-1.0.2.dist-info/WHEEL
foxdemo_lib-1.0.2.dist-info/top_level.txt
foxdemo_lib-1.0.2.dist-info/RECORD
